aashto_calculator/__init__.py
aashto_calculator/design.py
aashto_calculator93-0.1.0.dist-info/METADATA
aashto_calculator93-0.1.0.dist-info/WHEEL
aashto_calculator93-0.1.0.dist-info/top_level.txt
aashto_calculator93-0.1.0.dist-info/RECORD
