Metadata-Version: 2.4
Name: aashto-calculator93
Version: 0.1.0
Summary: AASHTO 1993 pavement design calculator (Python + PDF report)
Author-email: David Tello <dtello@hobrasystems.com>
License: MIT
Requires-Python: >=3.8
Requires-Dist: matplotlib
Requires-Dist: reportlab
